arcp/__init__.py
arcp/__main__.py
arcp/api/agents.py
arcp/api/auth.py
arcp/api/dashboard.py
arcp/api/health.py
arcp/api/public.py
arcp/api/tokens.py
arcp/client.py
arcp/core/cleanup.py
arcp/core/config.py
arcp/core/dependencies.py
arcp/core/exceptions.py
arcp/core/middleware.py
arcp/core/registry.py
arcp/core/routes.py
arcp/core/startup.py
arcp/core/storage_adapter.py
arcp/core/token_service.py
arcp/models/__init__.py
arcp/models/agent.py
arcp/models/auth.py
arcp/models/dashboard.py
arcp/models/token.py
arcp/services/__init__.py
arcp/services/metrics.py
arcp/services/openai.py
arcp/services/redis.py
arcp/utils/__init__.py
arcp/utils/api_protection.py
arcp/utils/auth_logging.py
arcp/utils/logging.py
arcp/utils/rate_limiter.py
arcp/utils/security_sanitizer.py
arcp/utils/sessions.py
arcp/utils/tracing.py
web/__init__.py
web/static/css/dashboard.css
web/static/icons/favicon.svg
web/static/js/chart.min.js
web/static/js/dashboard.js
web/static/js/secmanager.js
web/templates/index.html
arcp_py-2.0.3.dist-info/LICENSE
arcp_py-2.0.3.dist-info/METADATA
arcp_py-2.0.3.dist-info/WHEEL
arcp_py-2.0.3.dist-info/RECORD
